encodify/__init__.py
encodify-1.0.4.dist-info/LICENSE
encodify-1.0.4.dist-info/METADATA
encodify-1.0.4.dist-info/WHEEL
encodify-1.0.4.dist-info/top_level.txt
encodify-1.0.4.dist-info/RECORD
