Metadata-Version: 2.1
Name: encodify
Version: 1.0.4
Summary: A module for encoding and encrypting data.
Home-page: https://github.com/ishanoshada/encodify
Author: Ishan Oshada
Author-email: ic31908@gmail.com
Classifier: Programming Language :: Python :: 3
Classifier: License :: OSI Approved :: MIT License
Classifier: Operating System :: OS Independent
License-File: LICENSE
Requires-Dist: python-minifier
